alloniamodel/__init__.py
alloniamodel/checker.py
alloniamodel/decorator.py
alloniamodel/enums.py
alloniamodel/errors.py
alloniamodel/model.py
alloniamodel/utils.py
alloniamodel/variables.py
alloniamodel-1.4.7.dist-info/METADATA
alloniamodel-1.4.7.dist-info/WHEEL
alloniamodel-1.4.7.dist-info/RECORD
