Metadata-Version: 2.1
Name: alloniamodel
Version: 1.4.7
Summary: Class that wraps the notion of AI model to include an automatic persistence of trained models, with a complete history of their trainings and the associated metrics
Author: ALLONIA
Requires-Python: >=3.9,<4.0
Classifier: Programming Language :: Python :: 3
Classifier: Programming Language :: Python :: 3.9
Classifier: Programming Language :: Python :: 3.10
Classifier: Programming Language :: Python :: 3.11
Classifier: Programming Language :: Python :: 3.12
Requires-Dist: allonias3[datatypehandler] (>=1.7.0,<2.0.0)
Requires-Dist: scikit-learn (>=1.5.2,<2.0.0)
Requires-Dist: setuptools (>=75.1.0,<76.0.0)
